LICENSE
MANIFEST.in
README.rst
setup.py
django_inline_csv_importer.egg-info/PKG-INFO
django_inline_csv_importer.egg-info/SOURCES.txt
django_inline_csv_importer.egg-info/dependency_links.txt
django_inline_csv_importer.egg-info/requires.txt
django_inline_csv_importer.egg-info/top_level.txt
inline_csv_importer/__init__.py
inline_csv_importer/forms.py
inline_csv_importer/mixins.py
inline_csv_importer/templates/admin/inline_csv_importer/change_form.html
inline_csv_importer/templates/admin/inline_csv_importer/inline_csv_importer.html